pytest_lambda/__init__.py
pytest_lambda/compat.py
pytest_lambda/exceptions.py
pytest_lambda/fixtures.py
pytest_lambda/impl.py
pytest_lambda/plugin.py
pytest_lambda/py.typed
pytest_lambda/types.py
pytest_lambda/util.py
pytest_lambda-2.2.1.dist-info/LICENSE
pytest_lambda-2.2.1.dist-info/METADATA
pytest_lambda-2.2.1.dist-info/WHEEL
pytest_lambda-2.2.1.dist-info/entry_points.txt
pytest_lambda-2.2.1.dist-info/RECORD
