Metadata-Version: 2.1
Name: pytest-lambda
Version: 2.2.1
Summary: Define pytest fixtures with lambda functions.
Home-page: https://github.com/theY4Kman/pytest-lambda
License: MIT
Keywords: pytest
Author: Zach "theY4Kman" Kanzler
Author-email: they4kman@gmail.com
Requires-Python: >=3.8.0,<4.0.0
Classifier: Development Status :: 5 - Production/Stable
Classifier: Framework :: Pytest
Classifier: License :: OSI Approved :: MIT License
Classifier: Programming Language :: Python
Classifier: Programming Language :: Python :: 3
Classifier: Programming Language :: Python :: 3.8
Classifier: Programming Language :: Python :: 3.9
Classifier: Programming Language :: Python :: 3.10
Classifier: Programming Language :: Python :: 3.11
Classifier: Programming Language :: Python :: 3.12
Classifier: Topic :: Software Development :: Testing
Requires-Dist: pytest (>=3.6,<9)
Requires-Dist: wrapt (>=1.11.0,<2.0.0)
Project-URL: Repository, https://github.com/theY4Kman/pytest-lambda
